interactovery/__init__.py
interactovery/clusterwrap.py
interactovery/interactovery.py
interactovery/openaiwrap.py
interactovery/transcripts.py
interactovery/utils.py
interactovery/vizwrap.py
interactovery/workspaces.py
interactovery-0.0.6.dist-info/LICENSE
interactovery-0.0.6.dist-info/METADATA
interactovery-0.0.6.dist-info/WHEEL
interactovery-0.0.6.dist-info/RECORD
